{
  "IDENTIFIER": "[a-zA-Z][a-zA-Z0-9]*",
  "IF": "if",
  "RETURN": "return",
  "FUN": "fun",
  "WHILE": "while",
  "BRCKTL": "(",
  "BRCKTR": ")",
  "SEMICOLON": ";",
  "ADD": "+",
  "SUB": "-",
  "EXP": "**",
  "DIV": "/",
  "MULT": "*",
  "MOD": "%",
  "EQEQ": "==",
  "EXCLEQ": "!=",
  "AND_GATE": "&&",
  "OR_GATE": "||",
  "INT_LITERAL": "[0-9]+",
  "DOUBLE_LITERAL": "[0-9]*\\.[0-9+]",
  "CHAR_LITERAL": "'[0-9a-zA-Z]'",
  "INT_TYPE": "int",
  "DOUBLE_TYPE": "double",
  "CHAR_TYPE": "char",
  "WHITESPACE": " ",
  "MULTLN_START": "{",
  "MULTLN_STOP": "}"
}